pycodecage/__init__.py
pycodecage/environment.py
pycodecage/exceptions.py
pycodecage/factories.py
pycodecage/test_case.py
pycodecage/utils.py
pycodecage-0.1.2.dist-info/METADATA
pycodecage-0.1.2.dist-info/WHEEL
pycodecage-0.1.2.dist-info/RECORD
