Metadata-Version: 2.1
Name: pycodecage
Version: 0.1.2
Summary: 
Author: iYasha
Author-email: 33287747+iYasha@users.noreply.github.com
Requires-Python: >=3.6,<3.12
Classifier: Programming Language :: Python :: 3
Classifier: Programming Language :: Python :: 3.6
Classifier: Programming Language :: Python :: 3.7
Classifier: Programming Language :: Python :: 3.8
Classifier: Programming Language :: Python :: 3.9
Classifier: Programming Language :: Python :: 3.10
Classifier: Programming Language :: Python :: 3.11
Requires-Dist: restrictedpython (>=6.1,<7.0)
